{
  "release": {
    "url": "https://api.github.com/repos/ZalithLauncher/ZalithLauncher2/releases/313582284",
    "assets_url": "https://api.github.com/repos/ZalithLauncher/ZalithLauncher2/releases/313582284/assets",
    "upload_url": "https://uploads.github.com/repos/ZalithLauncher/ZalithLauncher2/releases/313582284/assets{?name,label}",
    "html_url": "https://github.com/ZalithLauncher/ZalithLauncher2/releases/tag/2.4.1",
    "id": 313582284,
    "author": {
      "login": "MovTery",
      "id": 123115192,
      "node_id": "U_kgDOB1aWuA",
      "avatar_url": "https://avatars.githubusercontent.com/u/123115192?v=4",
      "gravatar_id": "",
      "url": "https://api.github.com/users/MovTery",
      "html_url": "https://github.com/MovTery",
      "followers_url": "https://api.github.com/users/MovTery/followers",
      "following_url": "https://api.github.com/users/MovTery/following{/other_user}",
      "gists_url": "https://api.github.com/users/MovTery/gists{/gist_id}",
      "starred_url": "https://api.github.com/users/MovTery/starred{/owner}{/repo}",
      "subscriptions_url": "https://api.github.com/users/MovTery/subscriptions",
      "organizations_url": "https://api.github.com/users/MovTery/orgs",
      "repos_url": "https://api.github.com/users/MovTery/repos",
      "events_url": "https://api.github.com/users/MovTery/events{/privacy}",
      "received_events_url": "https://api.github.com/users/MovTery/received_events",
      "type": "User",
      "user_view_type": "public",
      "site_admin": false
    },
    "node_id": "RE_kwDOON0GPs4SsOLM",
    "tag_name": "2.4.1",
    "target_commitish": "main",
    "name": "2.4.1",
    "draft": false,
    "immutable": false,
    "prerelease": false,
    "created_at": "2026-04-25T13:10:46Z",
    "updated_at": "2026-04-25T13:19:11Z",
    "published_at": "2026-04-25T13:11:52Z",
    "assets": [
      {
        "url": "https://api.github.com/repos/ZalithLauncher/ZalithLauncher2/releases/assets/405326172",
        "id": 405326172,
        "node_id": "RA_kwDOON0GPs4YKMlc",
        "name": "ZalithLauncher-2.4.1-arm64-v8a.apk",
        "label": "",
        "uploader": {
          "login": "github-actions[bot]",
          "id": 41898282,
          "node_id": "MDM6Qm90NDE4OTgyODI=",
          "avatar_url": "https://avatars.githubusercontent.com/in/15368?v=4",
          "gravatar_id": "",
          "url": "https://api.github.com/users/github-actions%5Bbot%5D",
          "html_url": "https://github.com/apps/github-actions",
          "followers_url": "https://api.github.com/users/github-actions%5Bbot%5D/followers",
          "following_url": "https://api.github.com/users/github-actions%5Bbot%5D/following{/other_user}",
          "gists_url": "https://api.github.com/users/github-actions%5Bbot%5D/gists{/gist_id}",
          "starred_url": "https://api.github.com/users/github-actions%5Bbot%5D/starred{/owner}{/repo}",
          "subscriptions_url": "https://api.github.com/users/github-actions%5Bbot%5D/subscriptions",
          "organizations_url": "https://api.github.com/users/github-actions%5Bbot%5D/orgs",
          "repos_url": "https://api.github.com/users/github-actions%5Bbot%5D/repos",
          "events_url": "https://api.github.com/users/github-actions%5Bbot%5D/events{/privacy}",
          "received_events_url": "https://api.github.com/users/github-actions%5Bbot%5D/received_events",
          "type": "Bot",
          "user_view_type": "public",
          "site_admin": false
        },
        "content_type": "application/vnd.android.package-archive",
        "state": "uploaded",
        "size": 186497973,
        "digest": "sha256:e2a06aeae0df55b204bdebdb73bb694ded3019b44d166d9cd2882d21511c1267",
        "download_count": 8591,
        "created_at": "2026-04-25T13:18:53Z",
        "updated_at": "2026-04-25T13:19:04Z",
        "browser_download_url": "https://github.com/ZalithLauncher/ZalithLauncher2/releases/download/2.4.1/ZalithLauncher-2.4.1-arm64-v8a.apk"
      },
      {
        "url": "https://api.github.com/repos/ZalithLauncher/ZalithLauncher2/releases/assets/405326171",
        "id": 405326171,
        "node_id": "RA_kwDOON0GPs4YKMlb",
        "name": "ZalithLauncher-2.4.1-armeabi-v7a.apk",
        "label": "",
        "uploader": {
          "login": "github-actions[bot]",
          "id": 41898282,
          "node_id": "MDM6Qm90NDE4OTgyODI=",
          "avatar_url": "https://avatars.githubusercontent.com/in/15368?v=4",
          "gravatar_id": "",
          "url": "https://api.github.com/users/github-actions%5Bbot%5D",
          "html_url": "https://github.com/apps/github-actions",
          "followers_url": "https://api.github.com/users/github-actions%5Bbot%5D/followers",
          "following_url": "https://api.github.com/users/github-actions%5Bbot%5D/following{/other_user}",
          "gists_url": "https://api.github.com/users/github-actions%5Bbot%5D/gists{/gist_id}",
          "starred_url": "https://api.github.com/users/github-actions%5Bbot%5D/starred{/owner}{/repo}",
          "subscriptions_url": "https://api.github.com/users/github-actions%5Bbot%5D/subscriptions",
          "organizations_url": "https://api.github.com/users/github-actions%5Bbot%5D/orgs",
          "repos_url": "https://api.github.com/users/github-actions%5Bbot%5D/repos",
          "events_url": "https://api.github.com/users/github-actions%5Bbot%5D/events{/privacy}",
          "received_events_url": "https://api.github.com/users/github-actions%5Bbot%5D/received_events",
          "type": "Bot",
          "user_view_type": "public",
          "site_admin": false
        },
        "content_type": "application/vnd.android.package-archive",
        "state": "uploaded",
        "size": 180154428,
        "digest": "sha256:0e0073d21bc0520efdf2addf47b6995c27e28a05707e47db14a5b7dd2aac69d2",
        "download_count": 307,
        "created_at": "2026-04-25T13:18:53Z",
        "updated_at": "2026-04-25T13:19:03Z",
        "browser_download_url": "https://github.com/ZalithLauncher/ZalithLauncher2/releases/download/2.4.1/ZalithLauncher-2.4.1-armeabi-v7a.apk"
      },
      {
        "url": "https://api.github.com/repos/ZalithLauncher/ZalithLauncher2/releases/assets/405326170",
        "id": 405326170,
        "node_id": "RA_kwDOON0GPs4YKMla",
        "name": "ZalithLauncher-2.4.1-x86.apk",
        "label": "",
        "uploader": {
          "login": "github-actions[bot]",
          "id": 41898282,
          "node_id": "MDM6Qm90NDE4OTgyODI=",
          "avatar_url": "https://avatars.githubusercontent.com/in/15368?v=4",
          "gravatar_id": "",
          "url": "https://api.github.com/users/github-actions%5Bbot%5D",
          "html_url": "https://github.com/apps/github-actions",
          "followers_url": "https://api.github.com/users/github-actions%5Bbot%5D/followers",
          "following_url": "https://api.github.com/users/github-actions%5Bbot%5D/following{/other_user}",
          "gists_url": "https://api.github.com/users/github-actions%5Bbot%5D/gists{/gist_id}",
          "starred_url": "https://api.github.com/users/github-actions%5Bbot%5D/starred{/owner}{/repo}",
          "subscriptions_url": "https://api.github.com/users/github-actions%5Bbot%5D/subscriptions",
          "organizations_url": "https://api.github.com/users/github-actions%5Bbot%5D/orgs",
          "repos_url": "https://api.github.com/users/github-actions%5Bbot%5D/repos",
          "events_url": "https://api.github.com/users/github-actions%5Bbot%5D/events{/privacy}",
          "received_events_url": "https://api.github.com/users/github-actions%5Bbot%5D/received_events",
          "type": "Bot",
          "user_view_type": "public",
          "site_admin": false
        },
        "content_type": "application/vnd.android.package-archive",
        "state": "uploaded",
        "size": 171590029,
        "digest": "sha256:836e67e98d3fd41649674cb0aa326bf6179a56d3ed169bc668e56be4b4e3332c",
        "download_count": 149,
        "created_at": "2026-04-25T13:18:53Z",
        "updated_at": "2026-04-25T13:19:02Z",
        "browser_download_url": "https://github.com/ZalithLauncher/ZalithLauncher2/releases/download/2.4.1/ZalithLauncher-2.4.1-x86.apk"
      },
      {
        "url": "https://api.github.com/repos/ZalithLauncher/ZalithLauncher2/releases/assets/405326168",
        "id": 405326168,
        "node_id": "RA_kwDOON0GPs4YKMlY",
        "name": "ZalithLauncher-2.4.1-x86_64.apk",
        "label": "",
        "uploader": {
          "login": "github-actions[bot]",
          "id": 41898282,
          "node_id": "MDM6Qm90NDE4OTgyODI=",
          "avatar_url": "https://avatars.githubusercontent.com/in/15368?v=4",
          "gravatar_id": "",
          "url": "https://api.github.com/users/github-actions%5Bbot%5D",
          "html_url": "https://github.com/apps/github-actions",
          "followers_url": "https://api.github.com/users/github-actions%5Bbot%5D/followers",
          "following_url": "https://api.github.com/users/github-actions%5Bbot%5D/following{/other_user}",
          "gists_url": "https://api.github.com/users/github-actions%5Bbot%5D/gists{/gist_id}",
          "starred_url": "https://api.github.com/users/github-actions%5Bbot%5D/starred{/owner}{/repo}",
          "subscriptions_url": "https://api.github.com/users/github-actions%5Bbot%5D/subscriptions",
          "organizations_url": "https://api.github.com/users/github-actions%5Bbot%5D/orgs",
          "repos_url": "https://api.github.com/users/github-actions%5Bbot%5D/repos",
          "events_url": "https://api.github.com/users/github-actions%5Bbot%5D/events{/privacy}",
          "received_events_url": "https://api.github.com/users/github-actions%5Bbot%5D/received_events",
          "type": "Bot",
          "user_view_type": "public",
          "site_admin": false
        },
        "content_type": "application/vnd.android.package-archive",
        "state": "uploaded",
        "size": 190636278,
        "digest": "sha256:611bfdb06702dc7e904c709c70fefb5e94f232082e6935ab4fa631ae25a0139b",
        "download_count": 134,
        "created_at": "2026-04-25T13:18:53Z",
        "updated_at": "2026-04-25T13:19:04Z",
        "browser_download_url": "https://github.com/ZalithLauncher/ZalithLauncher2/releases/download/2.4.1/ZalithLauncher-2.4.1-x86_64.apk"
      },
      {
        "url": "https://api.github.com/repos/ZalithLauncher/ZalithLauncher2/releases/assets/405326169",
        "id": 405326169,
        "node_id": "RA_kwDOON0GPs4YKMlZ",
        "name": "ZalithLauncher-2.4.1.apk",
        "label": "",
        "uploader": {
          "login": "github-actions[bot]",
          "id": 41898282,
          "node_id": "MDM6Qm90NDE4OTgyODI=",
          "avatar_url": "https://avatars.githubusercontent.com/in/15368?v=4",
          "gravatar_id": "",
          "url": "https://api.github.com/users/github-actions%5Bbot%5D",
          "html_url": "https://github.com/apps/github-actions",
          "followers_url": "https://api.github.com/users/github-actions%5Bbot%5D/followers",
          "following_url": "https://api.github.com/users/github-actions%5Bbot%5D/following{/other_user}",
          "gists_url": "https://api.github.com/users/github-actions%5Bbot%5D/gists{/gist_id}",
          "starred_url": "https://api.github.com/users/github-actions%5Bbot%5D/starred{/owner}{/repo}",
          "subscriptions_url": "https://api.github.com/users/github-actions%5Bbot%5D/subscriptions",
          "organizations_url": "https://api.github.com/users/github-actions%5Bbot%5D/orgs",
          "repos_url": "https://api.github.com/users/github-actions%5Bbot%5D/repos",
          "events_url": "https://api.github.com/users/github-actions%5Bbot%5D/events{/privacy}",
          "received_events_url": "https://api.github.com/users/github-actions%5Bbot%5D/received_events",
          "type": "Bot",
          "user_view_type": "public",
          "site_admin": false
        },
        "content_type": "application/vnd.android.package-archive",
        "state": "uploaded",
        "size": 322838650,
        "digest": "sha256:ce60dceb2c0b616a7c3330c34771b93ac6e16f186f2865a8abd5e87e66a28793",
        "download_count": 1634,
        "created_at": "2026-04-25T13:18:53Z",
        "updated_at": "2026-04-25T13:19:11Z",
        "browser_download_url": "https://github.com/ZalithLauncher/ZalithLauncher2/releases/download/2.4.1/ZalithLauncher-2.4.1.apk"
      }
    ],
    "tarball_url": "https://api.github.com/repos/ZalithLauncher/ZalithLauncher2/tarball/2.4.1",
    "zipball_url": "https://api.github.com/repos/ZalithLauncher/ZalithLauncher2/zipball/2.4.1",
    "body": "## Notes:\r\n- Since version 26.2+, Mojang has introduced the Vulkan rendering engine. If your device does **not** support **Vulkan 1.2**, please do **not** use the **Vulkan backend** to launch the latest version of Minecraft.\r\n\r\n## Updates:\r\n- [GP#1112](https://github.com/ZalithLauncher/ZalithLauncher2/pull/1112): Synced translations from [Weblate project](https://hosted.weblate.org/projects/zalithlauncher2/)\r\n- [GP#1074](https://github.com/ZalithLauncher/ZalithLauncher2/pull/1074): Use concurrency to check for updates when updating mods. by youfeng11\r\n- [GP#1078](https://github.com/ZalithLauncher/ZalithLauncher2/pull/1078): Added Korean language option. by youfeng11\r\n- [GP#1080](https://github.com/ZalithLauncher/ZalithLauncher2/pull/1080): Added screenshot manager to view/save all in-game screenshots. by youfeng11, MovTery\r\n- [GP#1095](https://github.com/ZalithLauncher/ZalithLauncher2/pull/1095): Removed high-overhead theme switch transition animations, only transition when toggling dark mode. by MovTery\r\n- [GP#1099](https://github.com/ZalithLauncher/ZalithLauncher2/pull/1099): Rewrote full-screen exit implementation to support SDK 35. by youfeng11, MovTery\r\n- [GP#1103](https://github.com/ZalithLauncher/ZalithLauncher2/pull/1103): Added extraction task description for JNA dependency project. by MovTery\r\n\r\n## Refactors:\r\n- [GP#1072](https://github.com/ZalithLauncher/ZalithLauncher2/pull/1072): Do not enable domestic mirrors when downloading resources outside of China. by MovTery\r\n- [GP#1083](https://github.com/ZalithLauncher/ZalithLauncher2/pull/1083), [GP#1107](https://github.com/ZalithLauncher/ZalithLauncher2/pull/1107): Refactored launcher theme to better align with [Material 3 Expressive](https://m3.material.io/blog/building-with-m3-expressive) design standards. by MovTery\r\n\r\n## Changes:\r\n- [GP#1086](https://github.com/ZalithLauncher/ZalithLauncher2/pull/1086): Select All/Deselect All in Content Manager only applies to filtered results. by MovTery\r\n- [GP#1111](https://github.com/ZalithLauncher/ZalithLauncher2/pull/1111): Added ability to bypass account check through specific methods. by MovTery\r\n\r\n## Fixes:\r\n- [GP#1073](https://github.com/ZalithLauncher/ZalithLauncher2/pull/1073): Fixed issues where some devices could not properly exit full-screen, potentially causing touch position anomalies. by MovTery\r\n- [GP#1077](https://github.com/ZalithLauncher/ZalithLauncher2/pull/1077): Added support for updating mods by selecting the version based on the mod's own loader. by youfeng11\r\n- [GP#1089](https://github.com/ZalithLauncher/ZalithLauncher2/pull/1089): Game info display window can now be manually closed. by MovTery\r\n- [GP#1096](https://github.com/ZalithLauncher/ZalithLauncher2/pull/1096): Adapted foreground service type restrictions for Android 14. by MovTery\r\n- [GP#1106](https://github.com/ZalithLauncher/ZalithLauncher2/pull/1106): Fixed top bar being obscured when full-screening the app on ChromeOS. by youfeng11\r\n- [GP#1113](https://github.com/ZalithLauncher/ZalithLauncher2/pull/1113): Prevented OptiFine and similar versions from entering the update loader page. by MovTery",
    "reactions": {
      "url": "https://api.github.com/repos/ZalithLauncher/ZalithLauncher2/releases/313582284/reactions",
      "total_count": 3,
      "+1": 2,
      "-1": 0,
      "laugh": 0,
      "hooray": 1,
      "confused": 0,
      "heart": 0,
      "rocket": 0,
      "eyes": 0
    }
  },
  "action": {
    "run": {
      "id": 24957014813,
      "name": "Build CI",
      "node_id": "WFR_kwLOON0GPs8AAAAFz43THQ",
      "head_branch": "main",
      "head_sha": "20054dac5b12da4b4236c2a92c726fdfad3cd5a6",
      "path": ".github/workflows/push_ci.yml",
      "display_title": "Revert \"chore: 调整沉浸式实现\"",
      "run_number": 271,
      "event": "push",
      "status": "completed",
      "conclusion": "success",
      "workflow_id": 253303842,
      "check_suite_id": 66239279777,
      "check_suite_node_id": "CS_kwDOON0GPs8AAAAPbCsyoQ",
      "url": "https://api.github.com/repos/ZalithLauncher/ZalithLauncher2/actions/runs/24957014813",
      "html_url": "https://github.com/ZalithLauncher/ZalithLauncher2/actions/runs/24957014813",
      "pull_requests": [],
      "created_at": "2026-04-26T12:48:33Z",
      "updated_at": "2026-04-26T12:53:32Z",
      "actor": {
        "login": "MovTery",
        "id": 123115192,
        "node_id": "U_kgDOB1aWuA",
        "avatar_url": "https://avatars.githubusercontent.com/u/123115192?v=4",
        "gravatar_id": "",
        "url": "https://api.github.com/users/MovTery",
        "html_url": "https://github.com/MovTery",
        "followers_url": "https://api.github.com/users/MovTery/followers",
        "following_url": "https://api.github.com/users/MovTery/following{/other_user}",
        "gists_url": "https://api.github.com/users/MovTery/gists{/gist_id}",
        "starred_url": "https://api.github.com/users/MovTery/starred{/owner}{/repo}",
        "subscriptions_url": "https://api.github.com/users/MovTery/subscriptions",
        "organizations_url": "https://api.github.com/users/MovTery/orgs",
        "repos_url": "https://api.github.com/users/MovTery/repos",
        "events_url": "https://api.github.com/users/MovTery/events{/privacy}",
        "received_events_url": "https://api.github.com/users/MovTery/received_events",
        "type": "User",
        "user_view_type": "public",
        "site_admin": false
      },
      "run_attempt": 1,
      "referenced_workflows": [
        {
          "path": "ZalithLauncher/ZalithLauncher2/.github/workflows/build.yml@20054dac5b12da4b4236c2a92c726fdfad3cd5a6",
          "sha": "20054dac5b12da4b4236c2a92c726fdfad3cd5a6",
          "ref": "refs/heads/main"
        }
      ],
      "run_started_at": "2026-04-26T12:48:33Z",
      "triggering_actor": {
        "login": "MovTery",
        "id": 123115192,
        "node_id": "U_kgDOB1aWuA",
        "avatar_url": "https://avatars.githubusercontent.com/u/123115192?v=4",
        "gravatar_id": "",
        "url": "https://api.github.com/users/MovTery",
        "html_url": "https://github.com/MovTery",
        "followers_url": "https://api.github.com/users/MovTery/followers",
        "following_url": "https://api.github.com/users/MovTery/following{/other_user}",
        "gists_url": "https://api.github.com/users/MovTery/gists{/gist_id}",
        "starred_url": "https://api.github.com/users/MovTery/starred{/owner}{/repo}",
        "subscriptions_url": "https://api.github.com/users/MovTery/subscriptions",
        "organizations_url": "https://api.github.com/users/MovTery/orgs",
        "repos_url": "https://api.github.com/users/MovTery/repos",
        "events_url": "https://api.github.com/users/MovTery/events{/privacy}",
        "received_events_url": "https://api.github.com/users/MovTery/received_events",
        "type": "User",
        "user_view_type": "public",
        "site_admin": false
      },
      "jobs_url": "https://api.github.com/repos/ZalithLauncher/ZalithLauncher2/actions/runs/24957014813/jobs",
      "logs_url": "https://api.github.com/repos/ZalithLauncher/ZalithLauncher2/actions/runs/24957014813/logs",
      "check_suite_url": "https://api.github.com/repos/ZalithLauncher/ZalithLauncher2/check-suites/66239279777",
      "artifacts_url": "https://api.github.com/repos/ZalithLauncher/ZalithLauncher2/actions/runs/24957014813/artifacts",
      "cancel_url": "https://api.github.com/repos/ZalithLauncher/ZalithLauncher2/actions/runs/24957014813/cancel",
      "rerun_url": "https://api.github.com/repos/ZalithLauncher/ZalithLauncher2/actions/runs/24957014813/rerun",
      "previous_attempt_url": null,
      "workflow_url": "https://api.github.com/repos/ZalithLauncher/ZalithLauncher2/actions/workflows/253303842",
      "head_commit": {
        "id": "20054dac5b12da4b4236c2a92c726fdfad3cd5a6",
        "tree_id": "96d60b9c5748130ac7f0f5d9332cc2fb860f0c60",
        "message": "Revert \"chore: 调整沉浸式实现\"",
        "timestamp": "2026-04-26T12:48:24Z",
        "author": {
          "name": "movte",
          "email": "movtery228@qq.com"
        },
        "committer": {
          "name": "movte",
          "email": "movtery228@qq.com"
        }
      },
      "repository": {
        "id": 954009150,
        "node_id": "R_kgDOON0GPg",
        "name": "ZalithLauncher2",
        "full_name": "ZalithLauncher/ZalithLauncher2",
        "private": false,
        "owner": {
          "login": "ZalithLauncher",
          "id": 190403391,
          "node_id": "O_kgDOC1lTPw",
          "avatar_url": "https://avatars.githubusercontent.com/u/190403391?v=4",
          "gravatar_id": "",
          "url": "https://api.github.com/users/ZalithLauncher",
          "html_url": "https://github.com/ZalithLauncher",
          "followers_url": "https://api.github.com/users/ZalithLauncher/followers",
          "following_url": "https://api.github.com/users/ZalithLauncher/following{/other_user}",
          "gists_url": "https://api.github.com/users/ZalithLauncher/gists{/gist_id}",
          "starred_url": "https://api.github.com/users/ZalithLauncher/starred{/owner}{/repo}",
          "subscriptions_url": "https://api.github.com/users/ZalithLauncher/subscriptions",
          "organizations_url": "https://api.github.com/users/ZalithLauncher/orgs",
          "repos_url": "https://api.github.com/users/ZalithLauncher/repos",
          "events_url": "https://api.github.com/users/ZalithLauncher/events{/privacy}",
          "received_events_url": "https://api.github.com/users/ZalithLauncher/received_events",
          "type": "Organization",
          "user_view_type": "public",
          "site_admin": false
        },
        "html_url": "https://github.com/ZalithLauncher/ZalithLauncher2",
        "description": "A Minecraft: Java Edition Launcher for Android",
        "fork": false,
        "url": "https://api.github.com/repos/ZalithLauncher/ZalithLauncher2",
        "forks_url": "https://api.github.com/repos/ZalithLauncher/ZalithLauncher2/forks",
        "keys_url": "https://api.github.com/repos/ZalithLauncher/ZalithLauncher2/keys{/key_id}",
        "collaborators_url": "https://api.github.com/repos/ZalithLauncher/ZalithLauncher2/collaborators{/collaborator}",
        "teams_url": "https://api.github.com/repos/ZalithLauncher/ZalithLauncher2/teams",
        "hooks_url": "https://api.github.com/repos/ZalithLauncher/ZalithLauncher2/hooks",
        "issue_events_url": "https://api.github.com/repos/ZalithLauncher/ZalithLauncher2/issues/events{/number}",
        "events_url": "https://api.github.com/repos/ZalithLauncher/ZalithLauncher2/events",
        "assignees_url": "https://api.github.com/repos/ZalithLauncher/ZalithLauncher2/assignees{/user}",
        "branches_url": "https://api.github.com/repos/ZalithLauncher/ZalithLauncher2/branches{/branch}",
        "tags_url": "https://api.github.com/repos/ZalithLauncher/ZalithLauncher2/tags",
        "blobs_url": "https://api.github.com/repos/ZalithLauncher/ZalithLauncher2/git/blobs{/sha}",
        "git_tags_url": "https://api.github.com/repos/ZalithLauncher/ZalithLauncher2/git/tags{/sha}",
        "git_refs_url": "https://api.github.com/repos/ZalithLauncher/ZalithLauncher2/git/refs{/sha}",
        "trees_url": "https://api.github.com/repos/ZalithLauncher/ZalithLauncher2/git/trees{/sha}",
        "statuses_url": "https://api.github.com/repos/ZalithLauncher/ZalithLauncher2/statuses/{sha}",
        "languages_url": "https://api.github.com/repos/ZalithLauncher/ZalithLauncher2/languages",
        "stargazers_url": "https://api.github.com/repos/ZalithLauncher/ZalithLauncher2/stargazers",
        "contributors_url": "https://api.github.com/repos/ZalithLauncher/ZalithLauncher2/contributors",
        "subscribers_url": "https://api.github.com/repos/ZalithLauncher/ZalithLauncher2/subscribers",
        "subscription_url": "https://api.github.com/repos/ZalithLauncher/ZalithLauncher2/subscription",
        "commits_url": "https://api.github.com/repos/ZalithLauncher/ZalithLauncher2/commits{/sha}",
        "git_commits_url": "https://api.github.com/repos/ZalithLauncher/ZalithLauncher2/git/commits{/sha}",
        "comments_url": "https://api.github.com/repos/ZalithLauncher/ZalithLauncher2/comments{/number}",
        "issue_comment_url": "https://api.github.com/repos/ZalithLauncher/ZalithLauncher2/issues/comments{/number}",
        "contents_url": "https://api.github.com/repos/ZalithLauncher/ZalithLauncher2/contents/{+path}",
        "compare_url": "https://api.github.com/repos/ZalithLauncher/ZalithLauncher2/compare/{base}...{head}",
        "merges_url": "https://api.github.com/repos/ZalithLauncher/ZalithLauncher2/merges",
        "archive_url": "https://api.github.com/repos/ZalithLauncher/ZalithLauncher2/{archive_format}{/ref}",
        "downloads_url": "https://api.github.com/repos/ZalithLauncher/ZalithLauncher2/downloads",
        "issues_url": "https://api.github.com/repos/ZalithLauncher/ZalithLauncher2/issues{/number}",
        "pulls_url": "https://api.github.com/repos/ZalithLauncher/ZalithLauncher2/pulls{/number}",
        "milestones_url": "https://api.github.com/repos/ZalithLauncher/ZalithLauncher2/milestones{/number}",
        "notifications_url": "https://api.github.com/repos/ZalithLauncher/ZalithLauncher2/notifications{?since,all,participating}",
        "labels_url": "https://api.github.com/repos/ZalithLauncher/ZalithLauncher2/labels{/name}",
        "releases_url": "https://api.github.com/repos/ZalithLauncher/ZalithLauncher2/releases{/id}",
        "deployments_url": "https://api.github.com/repos/ZalithLauncher/ZalithLauncher2/deployments"
      },
      "head_repository": {
        "id": 954009150,
        "node_id": "R_kgDOON0GPg",
        "name": "ZalithLauncher2",
        "full_name": "ZalithLauncher/ZalithLauncher2",
        "private": false,
        "owner": {
          "login": "ZalithLauncher",
          "id": 190403391,
          "node_id": "O_kgDOC1lTPw",
          "avatar_url": "https://avatars.githubusercontent.com/u/190403391?v=4",
          "gravatar_id": "",
          "url": "https://api.github.com/users/ZalithLauncher",
          "html_url": "https://github.com/ZalithLauncher",
          "followers_url": "https://api.github.com/users/ZalithLauncher/followers",
          "following_url": "https://api.github.com/users/ZalithLauncher/following{/other_user}",
          "gists_url": "https://api.github.com/users/ZalithLauncher/gists{/gist_id}",
          "starred_url": "https://api.github.com/users/ZalithLauncher/starred{/owner}{/repo}",
          "subscriptions_url": "https://api.github.com/users/ZalithLauncher/subscriptions",
          "organizations_url": "https://api.github.com/users/ZalithLauncher/orgs",
          "repos_url": "https://api.github.com/users/ZalithLauncher/repos",
          "events_url": "https://api.github.com/users/ZalithLauncher/events{/privacy}",
          "received_events_url": "https://api.github.com/users/ZalithLauncher/received_events",
          "type": "Organization",
          "user_view_type": "public",
          "site_admin": false
        },
        "html_url": "https://github.com/ZalithLauncher/ZalithLauncher2",
        "description": "A Minecraft: Java Edition Launcher for Android",
        "fork": false,
        "url": "https://api.github.com/repos/ZalithLauncher/ZalithLauncher2",
        "forks_url": "https://api.github.com/repos/ZalithLauncher/ZalithLauncher2/forks",
        "keys_url": "https://api.github.com/repos/ZalithLauncher/ZalithLauncher2/keys{/key_id}",
        "collaborators_url": "https://api.github.com/repos/ZalithLauncher/ZalithLauncher2/collaborators{/collaborator}",
        "teams_url": "https://api.github.com/repos/ZalithLauncher/ZalithLauncher2/teams",
        "hooks_url": "https://api.github.com/repos/ZalithLauncher/ZalithLauncher2/hooks",
        "issue_events_url": "https://api.github.com/repos/ZalithLauncher/ZalithLauncher2/issues/events{/number}",
        "events_url": "https://api.github.com/repos/ZalithLauncher/ZalithLauncher2/events",
        "assignees_url": "https://api.github.com/repos/ZalithLauncher/ZalithLauncher2/assignees{/user}",
        "branches_url": "https://api.github.com/repos/ZalithLauncher/ZalithLauncher2/branches{/branch}",
        "tags_url": "https://api.github.com/repos/ZalithLauncher/ZalithLauncher2/tags",
        "blobs_url": "https://api.github.com/repos/ZalithLauncher/ZalithLauncher2/git/blobs{/sha}",
        "git_tags_url": "https://api.github.com/repos/ZalithLauncher/ZalithLauncher2/git/tags{/sha}",
        "git_refs_url": "https://api.github.com/repos/ZalithLauncher/ZalithLauncher2/git/refs{/sha}",
        "trees_url": "https://api.github.com/repos/ZalithLauncher/ZalithLauncher2/git/trees{/sha}",
        "statuses_url": "https://api.github.com/repos/ZalithLauncher/ZalithLauncher2/statuses/{sha}",
        "languages_url": "https://api.github.com/repos/ZalithLauncher/ZalithLauncher2/languages",
        "stargazers_url": "https://api.github.com/repos/ZalithLauncher/ZalithLauncher2/stargazers",
        "contributors_url": "https://api.github.com/repos/ZalithLauncher/ZalithLauncher2/contributors",
        "subscribers_url": "https://api.github.com/repos/ZalithLauncher/ZalithLauncher2/subscribers",
        "subscription_url": "https://api.github.com/repos/ZalithLauncher/ZalithLauncher2/subscription",
        "commits_url": "https://api.github.com/repos/ZalithLauncher/ZalithLauncher2/commits{/sha}",
        "git_commits_url": "https://api.github.com/repos/ZalithLauncher/ZalithLauncher2/git/commits{/sha}",
        "comments_url": "https://api.github.com/repos/ZalithLauncher/ZalithLauncher2/comments{/number}",
        "issue_comment_url": "https://api.github.com/repos/ZalithLauncher/ZalithLauncher2/issues/comments{/number}",
        "contents_url": "https://api.github.com/repos/ZalithLauncher/ZalithLauncher2/contents/{+path}",
        "compare_url": "https://api.github.com/repos/ZalithLauncher/ZalithLauncher2/compare/{base}...{head}",
        "merges_url": "https://api.github.com/repos/ZalithLauncher/ZalithLauncher2/merges",
        "archive_url": "https://api.github.com/repos/ZalithLauncher/ZalithLauncher2/{archive_format}{/ref}",
        "downloads_url": "https://api.github.com/repos/ZalithLauncher/ZalithLauncher2/downloads",
        "issues_url": "https://api.github.com/repos/ZalithLauncher/ZalithLauncher2/issues{/number}",
        "pulls_url": "https://api.github.com/repos/ZalithLauncher/ZalithLauncher2/pulls{/number}",
        "milestones_url": "https://api.github.com/repos/ZalithLauncher/ZalithLauncher2/milestones{/number}",
        "notifications_url": "https://api.github.com/repos/ZalithLauncher/ZalithLauncher2/notifications{?since,all,participating}",
        "labels_url": "https://api.github.com/repos/ZalithLauncher/ZalithLauncher2/labels{/name}",
        "releases_url": "https://api.github.com/repos/ZalithLauncher/ZalithLauncher2/releases{/id}",
        "deployments_url": "https://api.github.com/repos/ZalithLauncher/ZalithLauncher2/deployments"
      }
    },
    "artifacts": [
      {
        "id": 6647549543,
        "node_id": "MDg6QXJ0aWZhY3Q2NjQ3NTQ5NTQz",
        "name": "debug apk (x86_64)",
        "size_in_bytes": 200116433,
        "url": "https://api.github.com/repos/ZalithLauncher/ZalithLauncher2/actions/artifacts/6647549543",
        "archive_download_url": "https://api.github.com/repos/ZalithLauncher/ZalithLauncher2/actions/artifacts/6647549543/zip",
        "expired": false,
        "digest": "sha256:0c4be067ec066b260046a03b70fa3738cbd66db9b34fcb68227e59c32f61b64c",
        "created_at": "2026-04-26T12:52:55Z",
        "updated_at": "2026-04-26T12:52:55Z",
        "expires_at": "2026-05-03T12:48:33Z",
        "workflow_run": {
          "id": 24957014813,
          "repository_id": 954009150,
          "head_repository_id": 954009150,
          "head_branch": "main",
          "head_sha": "20054dac5b12da4b4236c2a92c726fdfad3cd5a6"
        }
      },
      {
        "id": 6647549401,
        "node_id": "MDg6QXJ0aWZhY3Q2NjQ3NTQ5NDAx",
        "name": "debug apk (all)",
        "size_in_bytes": 339859702,
        "url": "https://api.github.com/repos/ZalithLauncher/ZalithLauncher2/actions/artifacts/6647549401",
        "archive_download_url": "https://api.github.com/repos/ZalithLauncher/ZalithLauncher2/actions/artifacts/6647549401/zip",
        "expired": false,
        "digest": "sha256:400c7e4572e8d1b62c509d79f910ee693118a6f179055c2d84910412005ef169",
        "created_at": "2026-04-26T12:52:53Z",
        "updated_at": "2026-04-26T12:52:53Z",
        "expires_at": "2026-05-03T12:48:33Z",
        "workflow_run": {
          "id": 24957014813,
          "repository_id": 954009150,
          "head_repository_id": 954009150,
          "head_branch": "main",
          "head_sha": "20054dac5b12da4b4236c2a92c726fdfad3cd5a6"
        }
      },
      {
        "id": 6647547491,
        "node_id": "MDg6QXJ0aWZhY3Q2NjQ3NTQ3NDkx",
        "name": "debug apk (x86)",
        "size_in_bytes": 179575192,
        "url": "https://api.github.com/repos/ZalithLauncher/ZalithLauncher2/actions/artifacts/6647547491",
        "archive_download_url": "https://api.github.com/repos/ZalithLauncher/ZalithLauncher2/actions/artifacts/6647547491/zip",
        "expired": false,
        "digest": "sha256:744bfb0bc57af56c94f7e4eda6839d7cdb9f5331d197456b3c8129573e8c7e48",
        "created_at": "2026-04-26T12:52:35Z",
        "updated_at": "2026-04-26T12:52:35Z",
        "expires_at": "2026-05-03T12:48:33Z",
        "workflow_run": {
          "id": 24957014813,
          "repository_id": 954009150,
          "head_repository_id": 954009150,
          "head_branch": "main",
          "head_sha": "20054dac5b12da4b4236c2a92c726fdfad3cd5a6"
        }
      },
      {
        "id": 6647547010,
        "node_id": "MDg6QXJ0aWZhY3Q2NjQ3NTQ3MDEw",
        "name": "debug apk (arm64)",
        "size_in_bytes": 195687261,
        "url": "https://api.github.com/repos/ZalithLauncher/ZalithLauncher2/actions/artifacts/6647547010",
        "archive_download_url": "https://api.github.com/repos/ZalithLauncher/ZalithLauncher2/actions/artifacts/6647547010/zip",
        "expired": false,
        "digest": "sha256:840946a37618933aeb79c5d35a3268deeb4ff3da06af86143b728909205716b6",
        "created_at": "2026-04-26T12:52:30Z",
        "updated_at": "2026-04-26T12:52:30Z",
        "expires_at": "2026-05-03T12:48:33Z",
        "workflow_run": {
          "id": 24957014813,
          "repository_id": 954009150,
          "head_repository_id": 954009150,
          "head_branch": "main",
          "head_sha": "20054dac5b12da4b4236c2a92c726fdfad3cd5a6"
        }
      },
      {
        "id": 6647546877,
        "node_id": "MDg6QXJ0aWZhY3Q2NjQ3NTQ2ODc3",
        "name": "debug apk (arm)",
        "size_in_bytes": 188523007,
        "url": "https://api.github.com/repos/ZalithLauncher/ZalithLauncher2/actions/artifacts/6647546877",
        "archive_download_url": "https://api.github.com/repos/ZalithLauncher/ZalithLauncher2/actions/artifacts/6647546877/zip",
        "expired": false,
        "digest": "sha256:57adf2f4f2b68f02f10771706afca499d041f39673238e786b91f40e9c3a751f",
        "created_at": "2026-04-26T12:52:29Z",
        "updated_at": "2026-04-26T12:52:29Z",
        "expires_at": "2026-05-03T12:48:33Z",
        "workflow_run": {
          "id": 24957014813,
          "repository_id": 954009150,
          "head_repository_id": 954009150,
          "head_branch": "main",
          "head_sha": "20054dac5b12da4b4236c2a92c726fdfad3cd5a6"
        }
      }
    ]
  }
}
